seaturtles/EQHazard.jar
seaturtles/Markhvida_Table_1.csv
seaturtles/Markhvida_variogram.json
seaturtles/__init__.py
seaturtles/base.py
seaturtles/constants.py
seaturtles/main.py
seaturtles-1.1.0.dist-info/LICENSE
seaturtles-1.1.0.dist-info/METADATA
seaturtles-1.1.0.dist-info/WHEEL
seaturtles-1.1.0.dist-info/top_level.txt
seaturtles-1.1.0.dist-info/RECORD
