Metadata-Version: 2.1
Name: seaturtles
Version: 1.1.0
Summary: Scenario Earthquakes and the Uncertainty in Regional-Level Estimates of Shaking intensities
Home-page: https://github.com/annehulsey/seaturtles
Author: Anne Hulsey
Author-email: anne.hulsey@auckland.ac.nz
License: MIT License
Platform: any
Classifier: Programming Language :: Python
Classifier: Natural Language :: English
Classifier: Intended Audience :: Education
Classifier: Intended Audience :: Science/Research
Classifier: License :: OSI Approved :: MIT License
Classifier: Topic :: Scientific/Engineering
License-File: LICENSE
Requires-Dist: numpy
Requires-Dist: pandas
Requires-Dist: h5py
Requires-Dist: scipy
Requires-Dist: utm
